balance_sheet/__init__.py
balance_sheet/balanceSheet.py
balance_sheet/cli.py
balance_sheet/program.py
balance_sheet-1.1.0.dist-info/LICENSE
balance_sheet-1.1.0.dist-info/METADATA
balance_sheet-1.1.0.dist-info/WHEEL
balance_sheet-1.1.0.dist-info/entry_points.txt
balance_sheet-1.1.0.dist-info/top_level.txt
balance_sheet-1.1.0.dist-info/RECORD
